FreeKnowledge_AI/SearchResult.py
FreeKnowledge_AI/UrlSpecificCrawler.py
FreeKnowledge_AI/__init__.py
FreeKnowledge_AI/knowledge_center.py
FreeKnowledge_AI/prompt.py
FreeKnowledge_AI/sues_config.py
FreeKnowledge_AI/sues_search_baidu.py
FreeKnowledge_AI/sues_search_duckduckgo.py
FreeKnowledge_AI-0.3.1.dist-info/METADATA
FreeKnowledge_AI-0.3.1.dist-info/WHEEL
FreeKnowledge_AI-0.3.1.dist-info/top_level.txt
FreeKnowledge_AI-0.3.1.dist-info/RECORD
