Metadata-Version: 2.1
Name: FreeKnowledge_AI
Version: 0.3.1
Summary: An Agent for obtaining external knowledge for free.
Home-page: https://github.com/VovyH/FreeKnowledge_AI
Author: wuyuhang11
Author-email: m325124620@sues.edu.cn
License: MIT
Classifier: Programming Language :: Python :: 3
Classifier: License :: OSI Approved :: MIT License
Classifier: Operating System :: OS Independent
Requires-Python: >=3.10
Requires-Dist: requests >=2.25.1
Requires-Dist: beautifulsoup4 >=4.9.3
Requires-Dist: jieba >=0.42.1
Requires-Dist: matplotlib >=3.3.4
